endee_langchain/__init__.py
endee_langchain/base.py
endee_langchain-0.1.1.dist-info/METADATA
endee_langchain-0.1.1.dist-info/WHEEL
endee_langchain-0.1.1.dist-info/top_level.txt
endee_langchain-0.1.1.dist-info/RECORD
