Metadata-Version: 2.4
Name: endee-langchain
Version: 0.1.1
Summary: High Speed Vector Database for Faster and Efficient  ANN Searches with LangChain
Home-page: https://endee.io
Author: Endee Labs
Author-email: support@endee.io
Classifier: Programming Language :: Python :: 3
Classifier: License :: OSI Approved :: MIT License
Classifier: Operating System :: OS Independent
Requires-Python: >=3.6
Requires-Dist: langchain>=0.3.25
Requires-Dist: langchain-core>=0.3.59
Requires-Dist: endee>=0.1.4
Requires-Dist: numpy
Dynamic: author
Dynamic: author-email
Dynamic: classifier
Dynamic: description
Dynamic: description-content-type
Dynamic: home-page
Dynamic: requires-dist
Dynamic: requires-python
Dynamic: summary
